README.md
setup.cfg
setup.py
eis/__init__.py
eis/partner-portal/__init__.py
eis/partner-portal/api_client.py
eis/partner-portal/configuration.py
eis/partner-portal/exceptions.py
eis/partner-portal/model_utils.py
eis/partner-portal/rest.py
eis/partner-portal/api/__init__.py
eis/partner-portal/api/intermediary_api.py
eis/partner-portal/apis/__init__.py
eis/partner-portal/model/__init__.py
eis/partner-portal/model/account_class.py
eis/partner-portal/model/account_policy_class.py
eis/partner-portal/model/create_payment_method_request_dto.py
eis/partner-portal/model/create_policy_request_dto.py
eis/partner-portal/model/insured_object_type_class.py
eis/partner-portal/model/invoice_class.py
eis/partner-portal/model/invoice_item_class.py
eis/partner-portal/model/invoice_status_class.py
eis/partner-portal/model/lead_bank_account_class.py
eis/partner-portal/model/lead_class.py
eis/partner-portal/model/list_accounts_response_class.py
eis/partner-portal/model/list_leads_response_class.py
eis/partner-portal/model/list_partners_response_class.py
eis/partner-portal/model/list_policies_response_class.py
eis/partner-portal/model/omit_type_class.py
eis/partner-portal/model/partner_class.py
eis/partner-portal/model/partner_link_class.py
eis/partner-portal/model/partner_role_class.py
eis/partner-portal/model/policy_class.py
eis/partner-portal/model/policy_object_class.py
eis/partner-portal/model/policy_premium_class.py
eis/partner-portal/model/policy_premium_item_class.py
eis/partner-portal/model/policy_version_class.py
eis/partner-portal/model/premium_formula_class.py
eis/partner-portal/model/premium_override_dto.py
eis/partner-portal/model/premium_override_request_dto.py
eis/partner-portal/model/product_class.py
eis/partner-portal/model/product_version_class.py
eis/partner-portal/model/sepa_dto.py
eis/partner-portal/model/tag_class.py
eis/partner-portal/model/timeslice_class.py
eis/partner-portal/model/uploaded_document_dto.py
eis/partner-portal/models/__init__.py
eis_partner_portal.egg-info/PKG-INFO
eis_partner_portal.egg-info/SOURCES.txt
eis_partner_portal.egg-info/dependency_links.txt
eis_partner_portal.egg-info/requires.txt
eis_partner_portal.egg-info/top_level.txt
